s4g/__init__.py
s4g/__main__.py
s4g/macrosub.py
s4g/render.py
s4g-0.0.3.dist-info/LICENSE
s4g-0.0.3.dist-info/METADATA
s4g-0.0.3.dist-info/WHEEL
s4g-0.0.3.dist-info/entry_points.txt
s4g-0.0.3.dist-info/top_level.txt
s4g-0.0.3.dist-info/RECORD
